{"ticker": "BRK-B", "name": "Berkshire Hathaway Inc. New", "market": "US", "currency": "USD", "sector": "Financial Services", "industry": "Insurance - Diversified", "price": 495.5, "market_cap": 1068721045504.0, "roe": 0.10499, "roe_history": [0.09334572962243821, 0.13704863806039103, 0.1714370725119505, -0.04807318598127683], "gross_margin": 0.2778, "operating_margin": 0.14352, "net_margin": 0.19305, "revenue_cagr": 0.20586499585407747, "earnings_cagr": null, "debt_to_equity": 0.17669, "current_ratio": 2.876, "fcf": 61228249088.0, "fcf_yield": 0.05729114191732349, "dividend_yield": null, "per": 14.742636, "pbr": 0.0009801023, "eps": 33.61, "bps": 505559.44, "note": ""}