{"generated_epoch": 1784718930.8079045, "markets": {"kr": {"7": {"n": 20, "avg": -2.71, "mkt_avg": -4.38, "win_rate": 25.0, "best": {"name": "HDKSOE", "ret": 5.5}, "worst": {"name": "MCS", "ret": -10.1}, "asof_epoch": 1784112705}, "14": {"n": 19, "avg": -3.32, "mkt_avg": -3.6, "win_rate": 32.0, "best": {"name": "MCS", "ret": 9.4}, "worst": {"name": "JYP Ent.", "ret": -16.8}, "asof_epoch": 1783509083}, "30": {"n": 20, "avg": -6.77, "mkt_avg": -12.0, "win_rate": 25.0, "best": {"name": "COWAY", "ret": 6.7}, "worst": {"name": "JYP Ent.", "ret": -20.2}, "asof_epoch": 1782144417}}, "us": {"7": {"n": 8, "avg": 1.72, "mkt_avg": 0.04, "win_rate": 75.0, "best": {"name": "The Travelers Comp", "ret": 9.7}, "worst": {"name": "Progressive Corpor", "ret": -9.1}, "asof_epoch": 1784112644}, "14": {"n": 10, "avg": 1.27, "mkt_avg": -0.79, "win_rate": 50.0, "best": {"name": "The Travelers Comp", "ret": 7.5}, "worst": {"name": "Cincinnati Financi", "ret": -4.5}, "asof_epoch": 1783508759}, "30": {"n": 11, "avg": 10.9, "mkt_avg": 2.51, "win_rate": 91.0, "best": {"name": "The Travelers Comp", "ret": 19.0}, "worst": {"name": "Progressive Corpor", "ret": -0.7}, "asof_epoch": 1782159813}}}}